README.md
setup.py
NewFTP/FTPDownloader.py
NewFTP/NewFTP.pyw
NewFTP/PyFTPHandler.pyw
NewFTP/__init__.py
NewFTP/__main__.py
NewFTP/direction.py
NewFTP/finder.pyw
NewFTP/ftp_parser.py
NewFTP/messager.py
NewFTP.egg-info/PKG-INFO
NewFTP.egg-info/SOURCES.txt
NewFTP.egg-info/dependency_links.txt
NewFTP.egg-info/requires.txt
NewFTP.egg-info/top_level.txt
NewFTP/data/download_config.yaml
NewFTP/data/ftp_server.txt
NewFTP/data/gui_config.yaml
NewFTP/data/Styles/Git.yaml
NewFTP/data/Styles/MaterialBlue.yaml
NewFTP/data/Styles/MaterialGreen.yaml
NewFTP/data/Styles/Win7.yaml
NewFTP/data/Styles/Img/Git.jpg
NewFTP/data/Styles/Img/Win7.jpg