Metadata-Version: 2.1
Name: NewFTP
Version: 0.0.1
Summary: A GUI program to login the FTP system and a background program to manage FTP file downloading
Home-page: https://github.com/AllanChain/NewFTP
Author: AllanChain
Author-email: txsmlf@gmail.com
License: UNKNOWN
Platform: UNKNOWN
Classifier: Programming Language :: Python :: 3
Classifier: License :: OSI Approved :: GNU Affero General Public License v3
Classifier: Operating System :: Microsoft :: Windows :: Windows 7
Classifier: Development Status :: 3 - Alpha
